{
  "_class": "group",
  "do_objectID": "13BF4A5C-9727-43B2-BEC1-730CAE4B4FEA",
  "exportOptions": {
    "_class": "exportOptions",
    "do_objectID": "EFD57621-51A9-4D81-A935-42BBE2B4B737",
    "exportFormats": [
    ],
    "includedLayerIds": [
    ],
    "layerOptions": 0,
    "shouldTrim": false
  },
  "frame": {
    "_class": "rect",
    "constrainProportions": false,
    "do_objectID": "C8EBC010-8072-40AA-8DFB-D9F8B5A2302D",
    "height": 514,
    "width": 1440,
    "x": 0,
    "y": 510
  },
  "hasClickThrough": false,
  "isFlippedHorizontal": false,
  "isFlippedVertical": false,
  "isLocked": false,
  "isVisible": true,
  "layerListExpandedType": 2,
  "layers": [
    {
      "class": "group",
      "id": "19CB7DD3-2391-4B98-B5AF-0616543CF620"
    },
    {
      "class": "group",
      "id": "767CC84D-2220-4ABB-845C-304AD2ADE670"
    },
    {
      "class": "text",
      "id": "80BFFA31-5AD4-422F-9608-379739A1407E"
    },
    {
      "class": "text",
      "id": "7DE679B5-2265-40CB-8242-D67F4FC27FFC"
    },
    {
      "class": "symbolInstance",
      "id": "6212DF75-F66B-450C-811A-0A19A150CD09"
    },
    {
      "class": "symbolInstance",
      "id": "1C443F42-1FA5-49FA-A921-032469E0C380"
    },
    {
      "class": "text",
      "id": "F2CC830B-85F8-4894-9B93-48D9B94CFFB5"
    },
    {
      "class": "symbolInstance",
      "id": "C854C0F9-65B2-4903-9CD4-F0C0113A99E6"
    },
    {
      "class": "group",
      "id": "D854F15B-98B7-47E7-8F00-B92149C27214"
    },
    {
      "class": "text",
      "id": "AD5AC5C9-CF27-4381-A45F-076ADCAD637A"
    }
  ],
  "name": "Group 2",
  "nameIsFixed": false,
  "resizingConstraint": 63,
  "resizingType": 0,
  "rotation": 0,
  "shouldBreakMaskChain": false,
  "style": {
    "_class": "style",
    "do_objectID": "0DDB649B-BEFF-45C8-BEE6-59A2F23E2269",
    "endDecorationType": 0,
    "miterLimit": 10,
    "startDecorationType": 0
  }
}