{
  "_class": "artboard",
  "backgroundColor": {
    "_class": "color",
    "alpha": 1,
    "blue": 1,
    "green": 1,
    "red": 1
  },
  "do_objectID": "F0BF681E-A70C-4618-A8FB-B3E633454A63",
  "exportOptions": {
    "_class": "exportOptions",
    "exportFormats": [
      {
        "_class": "exportFormat",
        "absoluteSize": 0,
        "fileFormat": "jpg",
        "name": "",
        "namingScheme": 0,
        "scale": 1,
        "visibleScaleType": 0
      }
    ],
    "includedLayerIds": [
    ],
    "layerOptions": 0,
    "shouldTrim": false
  },
  "frame": {
    "_class": "rect",
    "constrainProportions": false,
    "height": 1199,
    "width": 375,
    "x": 10392,
    "y": 1092
  },
  "hasBackgroundColor": false,
  "hasClickThrough": true,
  "horizontalRulerData": {
    "_class": "rulerData",
    "base": 0,
    "guides": [
    ]
  },
  "includeBackgroundColorInExport": true,
  "includeInCloudUpload": true,
  "isFlippedHorizontal": false,
  "isFlippedVertical": false,
  "isLocked": false,
  "isVisible": true,
  "layerListExpandedType": 0,
  "layers": [
    {
      "class": "symbolInstance",
      "id": "F4182D2C-5F79-4D99-BFB8-9BFEDA272A50"
    },
    {
      "class": "group",
      "id": "133E5904-59F7-40C7-82FD-745CBF54FD5C"
    },
    {
      "class": "group",
      "id": "5EEDFEC2-2B88-4866-92E0-C04E70BAD0D9"
    },
    {
      "class": "symbolInstance",
      "id": "58B91E2D-6896-48BF-9A00-032E5BC6C53F"
    },
    {
      "class": "text",
      "id": "740EB710-34DC-4D5A-90FA-9420D768F582"
    },
    {
      "class": "text",
      "id": "9B2D27C9-38EE-41EA-A57C-8A0B371844B8"
    },
    {
      "class": "shapeGroup",
      "id": "6179DFAB-48FB-4B7B-89AD-263A3140F9B3"
    },
    {
      "class": "shapeGroup",
      "id": "53B3E052-603C-4413-A8A6-07B8ECFB1875"
    },
    {
      "class": "text",
      "id": "CA7F7034-F032-4AAD-BFA0-6A2EE1FCFEFB"
    },
    {
      "class": "text",
      "id": "BA089949-7D26-4E2D-91DB-3F47D0378F66"
    },
    {
      "class": "text",
      "id": "93AF12BF-254B-4F7A-A5A1-B20A8EE82926"
    },
    {
      "class": "text",
      "id": "A9909C90-E95E-4D64-AA64-0D35D970AA10"
    },
    {
      "class": "group",
      "id": "98CE09F2-78B2-478C-9EB0-BEBA3CFC9D4B"
    },
    {
      "class": "group",
      "id": "A5FE39C5-91DD-47A9-944E-FE20087140C3"
    },
    {
      "class": "text",
      "id": "1AF8449E-54AC-4401-83C7-2A203DB5F3AD"
    },
    {
      "class": "text",
      "id": "3ECEB78F-7AEC-4CA8-B856-37952B920D27"
    },
    {
      "class": "shapeGroup",
      "id": "4398D1DC-0FC6-448C-A836-B841AAAA1794"
    },
    {
      "class": "text",
      "id": "CA22A971-34DF-46E2-A2DC-75DCEFF03D20"
    },
    {
      "class": "text",
      "id": "01CC4CB6-67F6-483F-8254-8E9CD10172F3"
    },
    {
      "class": "group",
      "id": "AEF61A24-2B0B-48C4-AB92-43106A545988"
    },
    {
      "class": "text",
      "id": "4EA97813-9261-49CF-8BE4-9C20D7B848E7"
    },
    {
      "class": "group",
      "id": "A53A6802-A7D9-47F9-B908-7C277212A7D1"
    },
    {
      "class": "group",
      "id": "E4C7AF78-E7CB-4B76-A2A7-C5606D26B9E5"
    },
    {
      "class": "symbolInstance",
      "id": "14D0DE96-2061-48CB-AB15-ED7B60C2DDF8"
    },
    {
      "class": "text",
      "id": "A1E04F88-D76D-4F03-AB6A-C1A2DF6B3901"
    },
    {
      "class": "text",
      "id": "FF164384-91B5-4E96-A1C9-C00A14D394A3"
    },
    {
      "class": "text",
      "id": "66B57CE3-D840-4184-A9D9-5FFC7F9CF9FA"
    },
    {
      "class": "shapeGroup",
      "id": "4C731123-322A-45A5-8732-2DF47B83EE37"
    },
    {
      "class": "text",
      "id": "A15CE149-7EBF-48DD-9CF4-035412958144"
    },
    {
      "class": "shapeGroup",
      "id": "4CB13FAF-6BDF-4BBC-BBD8-40AA3D5542F1"
    },
    {
      "class": "text",
      "id": "4BA0D9BA-C57E-4A3D-8E34-7D23BDFE7376"
    },
    {
      "class": "text",
      "id": "436B473A-000D-412E-AD2F-F27C31F63218"
    },
    {
      "class": "symbolInstance",
      "id": "4AA937BE-4F80-45F9-ADD5-AA290B9E858A"
    },
    {
      "class": "symbolInstance",
      "id": "1FF4F209-A3DD-4EBB-BF86-D69EA7241979"
    },
    {
      "class": "symbolInstance",
      "id": "D0A73BAE-F268-4C8C-8901-4212EFDD4CED"
    },
    {
      "class": "shapeGroup",
      "id": "2C30D06A-CFA5-4774-90CE-97E86620C3EA"
    },
    {
      "class": "symbolInstance",
      "id": "3A8EAA79-18DF-4022-81ED-4057843E620F"
    },
    {
      "class": "shapeGroup",
      "id": "C26F3A54-0360-46FA-B8E7-C7392069ACA6"
    },
    {
      "class": "group",
      "id": "AA99583B-66A5-4802-AE42-5B11CCF011C1"
    }
  ],
  "name": "4.100-statement-mobile",
  "nameIsFixed": true,
  "resizesContent": false,
  "resizingConstraint": 63,
  "resizingType": 0,
  "rotation": 0,
  "shouldBreakMaskChain": false,
  "style": {
    "_class": "style",
    "endDecorationType": 0,
    "miterLimit": 10,
    "startDecorationType": 0
  },
  "userInfo": {
    "com.animaapp.stc-sketch-plugin": {
      "kModelPropertiesKey": {
      }
    }
  },
  "verticalRulerData": {
    "_class": "rulerData",
    "base": 0,
    "guides": [
    ]
  }
}