{
  "_class": "group",
  "do_objectID": "EDED554F-9E32-4F50-87FD-834FB069D4EE",
  "exportOptions": {
    "_class": "exportOptions",
    "do_objectID": "D9AB6FD2-6B72-462B-9C79-C5BC36AE8679",
    "exportFormats": [
    ],
    "includedLayerIds": [
    ],
    "layerOptions": 0,
    "shouldTrim": false
  },
  "frame": {
    "_class": "rect",
    "constrainProportions": false,
    "do_objectID": "D0E8BE9B-3346-47D7-9D3C-64389D944922",
    "height": 4.375000000000014,
    "width": 4.375000000000014,
    "x": 37.61333333333334,
    "y": 81.01333333333335
  },
  "hasClickThrough": false,
  "isFlippedHorizontal": false,
  "isFlippedVertical": false,
  "isLocked": false,
  "isVisible": true,
  "layerListExpandedType": 0,
  "layers": [
    {
      "class": "group",
      "id": "9F9A356C-FD77-46FD-B555-9395F6A80308"
    }
  ],
  "name": "Group",
  "nameIsFixed": false,
  "resizingConstraint": 63,
  "resizingType": 0,
  "rotation": 0,
  "shouldBreakMaskChain": false,
  "style": {
    "_class": "style",
    "blur": {
      "_class": "blur",
      "center": "{0.5, 0.5}",
      "do_objectID": "0307DC69-9322-4049-AEEA-220249DA93F4",
      "isEnabled": false,
      "motionAngle": 0,
      "radius": 4,
      "type": 0
    },
    "do_objectID": "10586227-D2FA-46AC-B6E1-812C336486D9",
    "endDecorationType": 0,
    "fills": [
      {
        "_class": "fill",
        "color": {
          "_class": "color",
          "alpha": 1,
          "blue": 0,
          "green": 0,
          "red": 0
        },
        "fillType": 0,
        "isEnabled": true,
        "noiseIndex": 0,
        "noiseIntensity": 0,
        "patternFillType": 1,
        "patternTileScale": 1
      }
    ],
    "miterLimit": 10,
    "startDecorationType": 0
  }
}