{
  "_class": "shapeGroup",
  "clippingMaskMode": 0,
  "do_objectID": "D5C561A4-906D-4752-BDC0-5D3F03DC5A0F",
  "exportOptions": {
    "_class": "exportOptions",
    "do_objectID": "DBD03E64-8583-448F-9269-33422FDF632E",
    "exportFormats": [
    ],
    "includedLayerIds": [
    ],
    "layerOptions": 0,
    "shouldTrim": false
  },
  "frame": {
    "_class": "rect",
    "constrainProportions": true,
    "do_objectID": "0BA66863-88E9-4C6C-A855-48FF144C674B",
    "height": 14,
    "width": 14,
    "x": 28,
    "y": 678
  },
  "hasClickThrough": false,
  "hasClippingMask": false,
  "isFlippedHorizontal": false,
  "isFlippedVertical": false,
  "isLocked": false,
  "isVisible": true,
  "layerListExpandedType": 1,
  "layers": [
    {
      "class": "oval",
      "id": "4DE3DEAF-BD9B-4F06-8F39-22694A16B5E4"
    }
  ],
  "name": "Oval 4",
  "nameIsFixed": false,
  "resizingConstraint": 63,
  "resizingType": 0,
  "rotation": 0,
  "shouldBreakMaskChain": false,
  "style": {
    "_class": "style",
    "borders": [
      {
        "_class": "border",
        "color": {
          "_class": "color",
          "alpha": 1,
          "blue": 0.592,
          "green": 0.592,
          "red": 0.592
        },
        "fillType": 0,
        "isEnabled": false,
        "position": 0,
        "thickness": 1
      }
    ],
    "do_objectID": "A87DCAF2-0DBF-4B44-BF16-F455B229B093",
    "endDecorationType": 0,
    "fills": [
      {
        "_class": "fill",
        "color": {
          "_class": "color",
          "alpha": 1,
          "blue": 0.3450980392156863,
          "green": 0.1058823529411765,
          "red": 0.1921568627450981
        },
        "fillType": 0,
        "isEnabled": true,
        "noiseIndex": 0,
        "noiseIntensity": 0,
        "patternFillType": 1,
        "patternTileScale": 1
      }
    ],
    "miterLimit": 10,
    "startDecorationType": 0
  },
  "userInfo": {
    "com.animaapp.stc-sketch-plugin": {
      "kModelPropertiesKey": {
        "constraints": {
          "aspectRatio": {
            "constant": 14,
            "enabled": 1,
            "modelID": "constraint_b4892993-1b4b-40a4-93d3-a6bf64950232",
            "model_class": "ADModelConstraint",
            "model_version": 0.1,
            "multiplier": 14
          },
          "automatic": 1,
          "modelID": "viewConstraints_14da5576-dc5d-4b94-89a9-c6fb143b1bc5",
          "model_class": "ADModelViewConstraints",
          "model_version": 0.1,
          "scaleFactor": 1
        }
      }
    }
  },
  "windingRule": 1
}