{
  "_class": "symbolInstance",
  "do_objectID": "9118E63D-B5F5-4885-9ECA-90E631E32125",
  "exportOptions": {
    "_class": "exportOptions",
    "do_objectID": "60B5D0FA-E653-47D5-9FFD-10DBC4B0D9E5",
    "exportFormats": [
    ],
    "includedLayerIds": [
    ],
    "layerOptions": 0,
    "shouldTrim": false
  },
  "frame": {
    "_class": "rect",
    "constrainProportions": false,
    "do_objectID": "0BF099A2-667D-44A8-BFA1-E8720195ADF4",
    "height": 24,
    "width": 24,
    "x": 20,
    "y": 624
  },
  "horizontalSpacing": 0,
  "isFlippedHorizontal": false,
  "isFlippedVertical": false,
  "isLocked": false,
  "isVisible": true,
  "layerListExpandedType": 0,
  "name": "icon/ui/chevron-left copy",
  "nameIsFixed": false,
  "overrideValues": [
  ],
  "overrides": {
  },
  "resizingConstraint": 63,
  "resizingType": 0,
  "rotation": 0,
  "scale": 1,
  "shouldBreakMaskChain": false,
  "style": {
    "_class": "style",
    "do_objectID": "45EB30DC-C7D8-4F6C-A019-6BAAB0549F4D",
    "endDecorationType": 0,
    "miterLimit": 10,
    "startDecorationType": 0
  },
  "symbolID": "4F52617D-E680-421E-A3F5-20A8EE56EAC3",
  "verticalSpacing": 0
}