{
  "_class": "group",
  "do_objectID": "6C4670D3-47F2-4D82-8D7F-8BFD4BF495AE",
  "exportOptions": {
    "_class": "exportOptions",
    "do_objectID": "9D7DB1A0-7A75-4C8A-8DEE-1C987CF98E1A",
    "exportFormats": [
    ],
    "includedLayerIds": [
    ],
    "layerOptions": 0,
    "shouldTrim": false
  },
  "frame": {
    "_class": "rect",
    "constrainProportions": false,
    "do_objectID": "D806303A-F72D-471B-B196-157D4E5A78DA",
    "height": 6,
    "width": 6,
    "x": 0,
    "y": 0
  },
  "hasClickThrough": false,
  "isFlippedHorizontal": false,
  "isFlippedVertical": false,
  "isLocked": false,
  "isVisible": true,
  "layerListExpandedType": 0,
  "layers": [
    {
      "class": "group",
      "id": "64CD4F21-9949-4495-9EE4-F541D4462BFA"
    }
  ],
  "name": "Group",
  "nameIsFixed": false,
  "resizingConstraint": 63,
  "resizingType": 0,
  "rotation": 0,
  "shouldBreakMaskChain": false,
  "style": {
    "_class": "style",
    "blur": {
      "_class": "blur",
      "center": "{0.5, 0.5}",
      "do_objectID": "C015CB44-2B9D-43AF-BBEA-1B347D34A0F1",
      "isEnabled": false,
      "motionAngle": 0,
      "radius": 4,
      "type": 0
    },
    "do_objectID": "78719831-B7AE-4884-8C96-BC698E567C88",
    "endDecorationType": 0,
    "fills": [
      {
        "_class": "fill",
        "color": {
          "_class": "color",
          "alpha": 1,
          "blue": 0.3450980392156863,
          "green": 0.1058823529411765,
          "red": 0.192156862745098
        },
        "fillType": 0,
        "isEnabled": true,
        "noiseIndex": 0,
        "noiseIntensity": 0,
        "patternFillType": 1,
        "patternTileScale": 1
      }
    ],
    "miterLimit": 10,
    "startDecorationType": 0
  }
}