{
  "_class": "group",
  "do_objectID": "D5DB0570-547B-4462-8DE0-E283473F8D0A",
  "exportOptions": {
    "_class": "exportOptions",
    "do_objectID": "CE426900-6A65-40C3-AB89-B7BAE61226A9",
    "exportFormats": [
    ],
    "includedLayerIds": [
    ],
    "layerOptions": 0,
    "shouldTrim": false
  },
  "frame": {
    "_class": "rect",
    "constrainProportions": false,
    "do_objectID": "D14B8A71-994E-41C8-A805-DFCF12F57EAA",
    "height": 250,
    "width": 250,
    "x": 0,
    "y": 0
  },
  "hasClickThrough": false,
  "isFlippedHorizontal": false,
  "isFlippedVertical": false,
  "isLocked": false,
  "isVisible": true,
  "layerListExpandedType": 0,
  "layers": [
    {
      "class": "group",
      "id": "4BD63EAF-C985-4C8D-86B6-98F01B398723"
    },
    {
      "class": "group",
      "id": "2E1C60E6-055F-4903-B290-C782C9B50416"
    }
  ],
  "name": "Group 3",
  "nameIsFixed": false,
  "resizingConstraint": 63,
  "resizingType": 0,
  "rotation": 0,
  "shouldBreakMaskChain": false,
  "style": {
    "_class": "style",
    "do_objectID": "73B9D060-35A0-4411-B417-C8E9ACF840FB",
    "endDecorationType": 0,
    "miterLimit": 10,
    "startDecorationType": 0
  },
  "userInfo": {
    "com.animaapp.stc-sketch-plugin": {
      "kModelPropertiesKey": {
      }
    }
  }
}