{
  "_class": "shapePath",
  "booleanOperation": -1,
  "do_objectID": "BD0D847C-601C-4CDC-AFF2-C0643A871A17",
  "edited": true,
  "exportOptions": {
    "_class": "exportOptions",
    "exportFormats": [
    ],
    "includedLayerIds": [
    ],
    "layerOptions": 0,
    "shouldTrim": false
  },
  "frame": {
    "_class": "rect",
    "constrainProportions": false,
    "height": 10,
    "width": 6,
    "x": 0,
    "y": 0
  },
  "isClosed": false,
  "isFlippedHorizontal": false,
  "isFlippedVertical": false,
  "isLocked": false,
  "isVisible": true,
  "layerListExpandedType": 0,
  "name": "Path",
  "nameIsFixed": false,
  "path": {
    "_class": "path",
    "isClosed": false,
    "pointRadiusBehaviour": 1,
    "points": [
      {
        "_class": "curvePoint",
        "cornerRadius": 0,
        "curveFrom": "{0, 0.20000000000000001}",
        "curveMode": 1,
        "curveTo": "{0, 0.20000000000000001}",
        "hasCurveFrom": false,
        "hasCurveTo": false,
        "point": "{0, 0.20000000000000001}"
      },
      {
        "_class": "curvePoint",
        "cornerRadius": 0,
        "curveFrom": "{1, 0.75}",
        "curveMode": 1,
        "curveTo": "{1, 0.75}",
        "hasCurveFrom": false,
        "hasCurveTo": false,
        "point": "{1, 0.75}"
      },
      {
        "_class": "curvePoint",
        "cornerRadius": 0,
        "curveFrom": "{0.49999999999999983, 1}",
        "curveMode": 1,
        "curveTo": "{0.49999999999999983, 1}",
        "hasCurveFrom": false,
        "hasCurveTo": false,
        "point": "{0.49999999999999983, 1}"
      },
      {
        "_class": "curvePoint",
        "cornerRadius": 0,
        "curveFrom": "{0.49999999999999994, 0}",
        "curveMode": 1,
        "curveTo": "{0.49999999999999994, 0}",
        "hasCurveFrom": false,
        "hasCurveTo": false,
        "point": "{0.49999999999999994, 0}"
      },
      {
        "_class": "curvePoint",
        "cornerRadius": 0,
        "curveFrom": "{1, 0.25}",
        "curveMode": 1,
        "curveTo": "{1, 0.25}",
        "hasCurveFrom": false,
        "hasCurveTo": false,
        "point": "{1, 0.25}"
      },
      {
        "_class": "curvePoint",
        "cornerRadius": 0,
        "curveFrom": "{0, 0.80000000000000004}",
        "curveMode": 1,
        "curveTo": "{0, 0.80000000000000004}",
        "hasCurveFrom": false,
        "hasCurveTo": false,
        "point": "{0, 0.80000000000000004}"
      }
    ]
  },
  "pointRadiusBehaviour": 1,
  "points": [
    {
      "_class": "curvePoint",
      "cornerRadius": 0,
      "curveFrom": "{0, 0.20000000000000001}",
      "curveMode": 1,
      "curveTo": "{0, 0.20000000000000001}",
      "hasCurveFrom": false,
      "hasCurveTo": false,
      "point": "{0, 0.20000000000000001}"
    },
    {
      "_class": "curvePoint",
      "cornerRadius": 0,
      "curveFrom": "{1, 0.75}",
      "curveMode": 1,
      "curveTo": "{1, 0.75}",
      "hasCurveFrom": false,
      "hasCurveTo": false,
      "point": "{1, 0.75}"
    },
    {
      "_class": "curvePoint",
      "cornerRadius": 0,
      "curveFrom": "{0.49999999999999983, 1}",
      "curveMode": 1,
      "curveTo": "{0.49999999999999983, 1}",
      "hasCurveFrom": false,
      "hasCurveTo": false,
      "point": "{0.49999999999999983, 1}"
    },
    {
      "_class": "curvePoint",
      "cornerRadius": 0,
      "curveFrom": "{0.49999999999999994, 0}",
      "curveMode": 1,
      "curveTo": "{0.49999999999999994, 0}",
      "hasCurveFrom": false,
      "hasCurveTo": false,
      "point": "{0.49999999999999994, 0}"
    },
    {
      "_class": "curvePoint",
      "cornerRadius": 0,
      "curveFrom": "{1, 0.25}",
      "curveMode": 1,
      "curveTo": "{1, 0.25}",
      "hasCurveFrom": false,
      "hasCurveTo": false,
      "point": "{1, 0.25}"
    },
    {
      "_class": "curvePoint",
      "cornerRadius": 0,
      "curveFrom": "{0, 0.80000000000000004}",
      "curveMode": 1,
      "curveTo": "{0, 0.80000000000000004}",
      "hasCurveFrom": false,
      "hasCurveTo": false,
      "point": "{0, 0.80000000000000004}"
    }
  ],
  "resizingConstraint": 63,
  "resizingType": 0,
  "rotation": 0,
  "shouldBreakMaskChain": false
}