{
  "_class": "group",
  "do_objectID": "D401D51A-7275-4644-873F-62AEB5F4CD7A",
  "exportOptions": {
    "_class": "exportOptions",
    "do_objectID": "4FDC6602-917B-4C8E-B845-A88C1E6461CD",
    "exportFormats": [
    ],
    "includedLayerIds": [
    ],
    "layerOptions": 0,
    "shouldTrim": false
  },
  "frame": {
    "_class": "rect",
    "constrainProportions": false,
    "do_objectID": "38DECCE2-7458-42EB-BC34-8A9A72468A91",
    "height": 50,
    "width": 1440,
    "x": 0,
    "y": 2
  },
  "hasClickThrough": false,
  "isFlippedHorizontal": false,
  "isFlippedVertical": false,
  "isLocked": false,
  "isVisible": true,
  "layerListExpandedType": 2,
  "layers": [
    {
      "class": "shapeGroup",
      "id": "07463FFE-DF53-4583-A7A6-0AEE35B3539E"
    }
  ],
  "name": "identity/collapsed-home-desktop",
  "nameIsFixed": false,
  "resizingConstraint": 63,
  "resizingType": 0,
  "rotation": 0,
  "shouldBreakMaskChain": false,
  "style": {
    "_class": "style",
    "do_objectID": "FB22C295-9AC2-403E-AB1F-67FBFA7F7A76",
    "endDecorationType": 0,
    "miterLimit": 10,
    "startDecorationType": 0
  }
}