{
  "_class": "group",
  "do_objectID": "0A551635-F51F-400E-8761-8686613C7C7E",
  "exportOptions": {
    "_class": "exportOptions",
    "do_objectID": "962D4CED-B856-47EF-A57E-14513B4E77FD",
    "exportFormats": [
    ],
    "includedLayerIds": [
    ],
    "layerOptions": 0,
    "shouldTrim": false
  },
  "frame": {
    "_class": "rect",
    "constrainProportions": false,
    "do_objectID": "F89BED69-915C-4C40-A9E7-B4EF41219563",
    "height": 4.375000000000028,
    "width": 4.375000000000014,
    "x": 73.77999999999999,
    "y": 153.3466666666667
  },
  "hasClickThrough": false,
  "isFlippedHorizontal": false,
  "isFlippedVertical": false,
  "isLocked": false,
  "isVisible": true,
  "layerListExpandedType": 0,
  "layers": [
    {
      "class": "group",
      "id": "4A1E8E9C-7418-4442-94AB-0B4EE5D7F8E1"
    }
  ],
  "name": "Group",
  "nameIsFixed": false,
  "resizingConstraint": 63,
  "resizingType": 0,
  "rotation": 0,
  "shouldBreakMaskChain": false,
  "style": {
    "_class": "style",
    "blur": {
      "_class": "blur",
      "center": "{0.5, 0.5}",
      "do_objectID": "4C21F959-4CF6-4AE9-BFF6-79A7E0A2D8EE",
      "isEnabled": false,
      "motionAngle": 0,
      "radius": 4,
      "type": 0
    },
    "do_objectID": "292DC21C-BACB-446A-A81B-8F4C02C82EFD",
    "endDecorationType": 0,
    "fills": [
      {
        "_class": "fill",
        "color": {
          "_class": "color",
          "alpha": 1,
          "blue": 0,
          "green": 0,
          "red": 0
        },
        "fillType": 0,
        "isEnabled": true,
        "noiseIndex": 0,
        "noiseIntensity": 0,
        "patternFillType": 1,
        "patternTileScale": 1
      }
    ],
    "miterLimit": 10,
    "startDecorationType": 0
  }
}