{
  "_class": "symbolInstance",
  "do_objectID": "35BADF2C-0257-4303-BBDE-326F6C4A6605",
  "exportOptions": {
    "_class": "exportOptions",
    "do_objectID": "0685DA76-42BA-4A94-967D-45B3FFCE728A",
    "exportFormats": [
    ],
    "includedLayerIds": [
    ],
    "layerOptions": 0,
    "shouldTrim": false
  },
  "frame": {
    "_class": "rect",
    "constrainProportions": false,
    "do_objectID": "89E6B5EC-67D1-4A10-B863-88401E8FFAEF",
    "height": 22,
    "width": 128,
    "x": 100,
    "y": 598
  },
  "horizontalSpacing": 0,
  "isFlippedHorizontal": false,
  "isFlippedVertical": false,
  "isLocked": false,
  "isVisible": true,
  "layerListExpandedType": 0,
  "name": "tag/dramatic",
  "nameIsFixed": false,
  "overrideValues": [
    {
      "_class": "overrideValue",
      "do_objectID": "BB67EABC-BD33-419B-AE33-DE9B76D5A07F",
      "overrideName": "4471F263-44FF-4D41-A482-0FFBACEEAD3D_stringValue",
      "value": "Oracle Register"
    }
  ],
  "resizingConstraint": 63,
  "resizingType": 0,
  "rotation": 0,
  "scale": 1,
  "shouldBreakMaskChain": false,
  "style": {
    "_class": "style",
    "do_objectID": "60EDCE65-54DC-4CB7-99D9-7827D10B5EAE",
    "endDecorationType": 0,
    "miterLimit": 10,
    "startDecorationType": 0
  },
  "symbolID": "167795BE-09D3-4D24-B72D-B89EF697F755",
  "userInfo": {
    "com.animaapp.stc-sketch-plugin": {
      "kModelPropertiesKey": {
      }
    }
  },
  "verticalSpacing": 0
}