{
  "_class": "group",
  "do_objectID": "61C0B1AB-688C-410C-AA04-9DC19F8CA923",
  "exportOptions": {
    "_class": "exportOptions",
    "do_objectID": "81B5B3A7-C573-4F40-80B6-4E953F10B9CC",
    "exportFormats": [
    ],
    "includedLayerIds": [
    ],
    "layerOptions": 0,
    "shouldTrim": false
  },
  "frame": {
    "_class": "rect",
    "constrainProportions": false,
    "do_objectID": "A7824FF6-CBF4-47AD-B362-F9C410685762",
    "height": 6,
    "width": 6,
    "x": 195.7218659517426,
    "y": 98.74256300268097
  },
  "hasClickThrough": false,
  "isFlippedHorizontal": false,
  "isFlippedVertical": false,
  "isLocked": false,
  "isVisible": true,
  "layerListExpandedType": 0,
  "layers": [
    {
      "class": "group",
      "id": "49F13C89-648F-4AA5-BE21-E659990DDCC3"
    }
  ],
  "name": "Group",
  "nameIsFixed": false,
  "resizingConstraint": 63,
  "resizingType": 0,
  "rotation": 0,
  "shouldBreakMaskChain": false,
  "style": {
    "_class": "style",
    "blur": {
      "_class": "blur",
      "center": "{0.5, 0.5}",
      "do_objectID": "AF487C68-8769-43A5-9D5B-E4B8BA181543",
      "isEnabled": false,
      "motionAngle": 0,
      "radius": 4,
      "type": 0
    },
    "do_objectID": "05100CC1-26BB-478E-90BE-FCCC39D3B005",
    "endDecorationType": 0,
    "fills": [
      {
        "_class": "fill",
        "color": {
          "_class": "color",
          "alpha": 1,
          "blue": 0,
          "green": 0,
          "red": 0
        },
        "fillType": 0,
        "isEnabled": true,
        "noiseIndex": 0,
        "noiseIntensity": 0,
        "patternFillType": 1,
        "patternTileScale": 1
      }
    ],
    "miterLimit": 10,
    "startDecorationType": 0
  }
}