{
  "_class": "group",
  "do_objectID": "CD41AE1A-5CFD-41E2-9EDD-915EBC8C27DD",
  "exportOptions": {
    "_class": "exportOptions",
    "do_objectID": "68CDBE99-BCFD-45D3-AEA7-FB5099BFF87B",
    "exportFormats": [
    ],
    "includedLayerIds": [
    ],
    "layerOptions": 0,
    "shouldTrim": false
  },
  "frame": {
    "_class": "rect",
    "constrainProportions": false,
    "do_objectID": "D80937A5-7B9F-40F6-AEDB-5D50D0BA4355",
    "height": 5,
    "width": 5,
    "x": 0,
    "y": 0
  },
  "hasClickThrough": false,
  "isFlippedHorizontal": false,
  "isFlippedVertical": false,
  "isLocked": false,
  "isVisible": true,
  "layerListExpandedType": 0,
  "layers": [
    {
      "class": "shapeGroup",
      "id": "94341A1F-2801-456C-BE65-AE18957CCBBF"
    }
  ],
  "name": "Group",
  "nameIsFixed": false,
  "resizingConstraint": 63,
  "resizingType": 0,
  "rotation": 0,
  "shouldBreakMaskChain": false,
  "style": {
    "_class": "style",
    "blur": {
      "_class": "blur",
      "center": "{0.5, 0.5}",
      "do_objectID": "BF263F48-AA7D-4BCC-A01A-7E9D5B316672",
      "isEnabled": false,
      "motionAngle": 0,
      "radius": 4,
      "type": 0
    },
    "do_objectID": "E0BD2A13-3B84-47EA-B333-1716B984968E",
    "endDecorationType": 0,
    "fills": [
      {
        "_class": "fill",
        "color": {
          "_class": "color",
          "alpha": 1,
          "blue": 0.3450980392156863,
          "green": 0.1058823529411765,
          "red": 0.192156862745098
        },
        "fillType": 0,
        "isEnabled": true,
        "noiseIndex": 0,
        "noiseIntensity": 0,
        "patternFillType": 1,
        "patternTileScale": 1
      }
    ],
    "miterLimit": 10,
    "startDecorationType": 0
  }
}