{
  "_class": "shapePath",
  "booleanOperation": -1,
  "do_objectID": "069A6524-3C7A-41D4-9213-657BE8EAE435",
  "edited": true,
  "exportOptions": {
    "_class": "exportOptions",
    "exportFormats": [
    ],
    "includedLayerIds": [
    ],
    "layerOptions": 0,
    "shouldTrim": false
  },
  "frame": {
    "_class": "rect",
    "constrainProportions": false,
    "height": 4.437220982142856,
    "width": 6.098622651218059,
    "x": 1.639148228661966,
    "y": 6.353655133928571
  },
  "isFlippedHorizontal": false,
  "isFlippedVertical": false,
  "isLocked": false,
  "isVisible": true,
  "layerListExpandedType": 0,
  "name": "Path",
  "nameIsFixed": false,
  "originalObjectID": "69D13DFE-1C53-42D8-BFF6-57DE5F40F2A9",
  "path": {
    "_class": "path",
    "isClosed": true,
    "pointRadiusBehaviour": 0,
    "points": [
      {
        "_class": "curvePoint",
        "cornerRadius": 0,
        "curveFrom": "{-0.0055226013237615603, 0.20430107526881708}",
        "curveMode": 2,
        "curveTo": "{0.0057554185137048842, 0.79569892473118276}",
        "hasCurveFrom": true,
        "hasCurveTo": true,
        "point": "{0.00011640859497515758, 0.49999999999999989}"
      },
      {
        "_class": "curvePoint",
        "cornerRadius": 0,
        "curveFrom": "{0.78445732122045386, 0}",
        "curveMode": 2,
        "curveTo": "{0.19421496749495964, 0}",
        "hasCurveFrom": true,
        "hasCurveTo": true,
        "point": "{0.48933614435770439, 0}"
      },
      {
        "_class": "curvePoint",
        "cornerRadius": 0,
        "curveFrom": "{1.0067640721806053, 0.79569892473118276}",
        "curveMode": 2,
        "curveTo": "{0.99288538784456337, 0.20430107526881708}",
        "hasCurveFrom": true,
        "hasCurveTo": true,
        "point": "{0.99982473001258199, 0.49999999999999989}"
      },
      {
        "_class": "curvePoint",
        "cornerRadius": 0,
        "curveFrom": "{0.21418278565839405, 1}",
        "curveMode": 4,
        "curveTo": "{0.80702720284131602, 1}",
        "hasCurveFrom": true,
        "hasCurveTo": true,
        "point": "{0.51060499424985961, 1}"
      }
    ]
  },
  "resizingConstraint": 63,
  "resizingType": 0,
  "rotation": 0,
  "shouldBreakMaskChain": false
}