{
  "_class": "symbolInstance",
  "do_objectID": "F0D9708B-F209-4E16-9826-E08A0C51C67A",
  "exportOptions": {
    "_class": "exportOptions",
    "do_objectID": "DF4478F5-0F73-4D6D-8CA7-CB348533008A",
    "exportFormats": [
    ],
    "includedLayerIds": [
    ],
    "layerOptions": 0,
    "shouldTrim": false
  },
  "frame": {
    "_class": "rect",
    "constrainProportions": false,
    "do_objectID": "A25F0DB6-C740-4009-94CD-9079B492CFA4",
    "height": 2,
    "width": 335,
    "x": 20,
    "y": 484
  },
  "horizontalSpacing": 0,
  "isFlippedHorizontal": false,
  "isFlippedVertical": false,
  "isLocked": false,
  "isVisible": true,
  "layerListExpandedType": 0,
  "name": "divider/divider",
  "nameIsFixed": false,
  "overrideValues": [
  ],
  "resizingConstraint": 63,
  "resizingType": 0,
  "rotation": 0,
  "scale": 1,
  "shouldBreakMaskChain": false,
  "style": {
    "_class": "style",
    "do_objectID": "10E80DF7-13A0-48AC-B44F-E828A85C5B19",
    "endDecorationType": 0,
    "miterLimit": 10,
    "startDecorationType": 0
  },
  "symbolID": "7BAEA60D-8219-4E8D-B3BF-1ED17E73B325",
  "userInfo": {
    "com.animaapp.stc-sketch-plugin": {
      "kModelPropertiesKey": {
      }
    }
  },
  "verticalSpacing": 0
}