{
  "_class": "text",
  "attributedString": {
    "_class": "attributedString",
    "attributes": [
      {
        "_class": "stringAttribute",
        "attributes": {
          "MSAttributedStringColorAttribute": {
            "_class": "color",
            "alpha": 1,
            "blue": 0.5960784314,
            "green": 0.5960784314,
            "red": 0.5960784314
          },
          "MSAttributedStringFontAttribute": {
            "_class": "fontDescriptor",
            "attributes": {
              "name": "Roboto-Medium",
              "size": 12
            }
          },
          "MSAttributedStringTextTransformAttribute": 1,
          "kerning": 0.300000011920929,
          "paragraphStyle": {
            "_class": "paragraphStyle",
            "alignment": 2,
            "maximumLineHeight": 16,
            "minimumLineHeight": 16
          }
        },
        "length": 80,
        "location": 0
      }
    ],
    "string": "You can change these settings in “details” in your Identity Manager at all times"
  },
  "automaticallyDrawOnUnderlyingPath": false,
  "do_objectID": "5A948BE6-9049-4CBF-8487-906E221BA264",
  "dontSynchroniseWithSymbol": false,
  "exportOptions": {
    "_class": "exportOptions",
    "exportFormats": [
    ],
    "includedLayerIds": [
    ],
    "layerOptions": 0,
    "shouldTrim": false
  },
  "frame": {
    "_class": "rect",
    "constrainProportions": false,
    "height": 32,
    "width": 300,
    "x": 38,
    "y": 855
  },
  "glyphBounds": "{{10, 1}, {280, 29}}",
  "isFlippedHorizontal": false,
  "isFlippedVertical": false,
  "isLocked": false,
  "isVisible": true,
  "layerListExpandedType": 0,
  "lineSpacingBehaviour": 1,
  "name": "You can change these",
  "nameIsFixed": false,
  "resizingConstraint": 47,
  "resizingType": 0,
  "rotation": 0,
  "shouldBreakMaskChain": false,
  "style": {
    "sharedObjectID": "1941A631-0FFA-4E5A-ADD8-5FDE0243B175"
  },
  "textBehaviour": 1,
  "userInfo": {
    "com.animaapp.stc-sketch-plugin": {
      "kModelPropertiesKey": {
        "isAutoWidth": 0
      }
    }
  }
}