{
  "_class": "shapeGroup",
  "clippingMaskMode": 0,
  "do_objectID": "C35179D6-69AA-41D8-94C1-184E5784CF1D",
  "exportOptions": {
    "_class": "exportOptions",
    "do_objectID": "06333ED1-DCCA-4235-B379-C7ABEB1D978D",
    "exportFormats": [
    ],
    "includedLayerIds": [
    ],
    "layerOptions": 0,
    "shouldTrim": false
  },
  "frame": {
    "_class": "rect",
    "constrainProportions": false,
    "do_objectID": "45A99085-9DE6-4F62-B6ED-5006F5B99F59",
    "height": 6.199335120643369,
    "width": 6.199335120643335,
    "x": 0,
    "y": 0
  },
  "hasClickThrough": false,
  "hasClippingMask": false,
  "isFlippedHorizontal": false,
  "isFlippedVertical": false,
  "isLocked": false,
  "isVisible": true,
  "layerListExpandedType": 1,
  "layers": [
    {
      "class": "oval",
      "id": "7974ECE2-6FAE-4D81-8B80-06DA0A789EAF"
    }
  ],
  "name": "Oval",
  "nameIsFixed": false,
  "resizingConstraint": 63,
  "resizingType": 0,
  "rotation": 0,
  "shouldBreakMaskChain": false,
  "style": {
    "_class": "style",
    "blur": {
      "_class": "blur",
      "center": "{0.5, 0.5}",
      "do_objectID": "BF6BC6D4-8D28-43B8-B4B0-3201C812DB48",
      "isEnabled": false,
      "motionAngle": 0,
      "radius": 4,
      "type": 0
    },
    "do_objectID": "54BC6BD3-8665-4373-81E2-26CF9DF8F393",
    "endDecorationType": 0,
    "fills": [
      {
        "_class": "fill",
        "color": {
          "_class": "color",
          "alpha": 1,
          "blue": 0.3450980392156863,
          "green": 0.1058823529411765,
          "red": 0.192156862745098
        },
        "fillType": 0,
        "isEnabled": true,
        "noiseIndex": 0,
        "noiseIntensity": 0,
        "patternFillType": 1,
        "patternTileScale": 1
      }
    ],
    "miterLimit": 10,
    "startDecorationType": 0
  },
  "windingRule": 0
}