{
  "_class": "artboard",
  "backgroundColor": {
    "_class": "color",
    "alpha": 1,
    "blue": 1,
    "do_objectID": "7EEEE2D8-0A0E-40E5-973E-BCA341F31E63",
    "green": 1,
    "red": 1
  },
  "do_objectID": "6058EE47-5577-4545-B72F-2667C9B096FF",
  "exportOptions": {
    "_class": "exportOptions",
    "do_objectID": "03580F1C-F229-4509-94FF-468168C16A14",
    "exportFormats": [
      {
        "_class": "exportFormat",
        "absoluteSize": 0,
        "fileFormat": "png",
        "name": "",
        "namingScheme": 0,
        "scale": 1,
        "visibleScaleType": 0
      }
    ],
    "includedLayerIds": [
    ],
    "layerOptions": 0,
    "shouldTrim": false
  },
  "frame": {
    "_class": "rect",
    "constrainProportions": false,
    "do_objectID": "7E915BAC-BD66-4DFB-9203-83AC98D58949",
    "height": 667,
    "width": 375,
    "x": 641,
    "y": 1625
  },
  "hasBackgroundColor": true,
  "hasClickThrough": false,
  "horizontalRulerData": {
    "_class": "rulerData",
    "base": 0,
    "do_objectID": "20809521-1372-47B6-82EA-FAAC086937EA",
    "guides": [
    ]
  },
  "includeBackgroundColorInExport": true,
  "includeInCloudUpload": true,
  "isFlippedHorizontal": false,
  "isFlippedVertical": false,
  "isFlowHome": false,
  "isLocked": false,
  "isVisible": true,
  "layerListExpandedType": 2,
  "layers": [
    {
      "class": "group",
      "id": "9B56C598-5B02-4EB6-9A1E-E28776159FF9"
    },
    {
      "class": "symbolInstance",
      "id": "64F13EA2-1E1C-48DE-A1CE-D439777FF778"
    },
    {
      "class": "group",
      "id": "5B169C3E-B37B-4464-BB92-586D3AD9FA85"
    },
    {
      "class": "symbolInstance",
      "id": "938F5BB1-F4D6-426F-88E4-446A99E89DDD"
    },
    {
      "class": "group",
      "id": "B1454ED8-DBE0-4274-9C1E-869FB4AC81AA"
    },
    {
      "class": "text",
      "id": "E71A12A5-9355-406F-A5C5-36448F6C3D63"
    }
  ],
  "name": "12.21-re:publica-scan",
  "nameIsFixed": true,
  "presetDictionary": {
    "allowResizedMatching": 1,
    "height": 667,
    "name": "iPhone 8",
    "offersLandscapeVariant": 1,
    "width": 375
  },
  "resizesContent": false,
  "resizingConstraint": 63,
  "resizingType": 0,
  "rotation": 0,
  "shouldBreakMaskChain": true,
  "style": {
    "_class": "style",
    "do_objectID": "5E9225EA-C58D-47DB-BF6D-ABDC6AE51254",
    "endDecorationType": 0,
    "fills": [
      {
        "_class": "fill",
        "color": {
          "_class": "color",
          "alpha": 1,
          "blue": 1,
          "green": 1,
          "red": 1
        },
        "fillType": 0,
        "isEnabled": true,
        "noiseIndex": 0,
        "noiseIntensity": 0,
        "patternFillType": 1,
        "patternTileScale": 1
      }
    ],
    "miterLimit": 10,
    "startDecorationType": 0
  },
  "userInfo": {
    "com.animaapp.stc-sketch-plugin": {
      "kModelPropertiesKey": {
      }
    }
  },
  "verticalRulerData": {
    "_class": "rulerData",
    "base": 0,
    "do_objectID": "CFC56F5C-4318-4BF4-AC5D-BE82CFD6689A",
    "guides": [
    ]
  }
}